littyping/__init__.py
littyping/_modidx.py
littyping/aliases.py
littyping/batched.py
littyping/constants.py
littyping/core.py
littyping/device.py
littyping/dims.py
littyping/dtype.py
littyping/errors.py
littyping/guards.py
littyping/meta.py
littyping/named_dims.py
littyping/pttype.py
littyping/shape.py
littyping/tensor.py
littyping/tests.py
littyping/utils.py
littyping-0.0.1.dist-info/LICENSE
littyping-0.0.1.dist-info/METADATA
littyping-0.0.1.dist-info/WHEEL
littyping-0.0.1.dist-info/entry_points.txt
littyping-0.0.1.dist-info/top_level.txt
littyping-0.0.1.dist-info/RECORD
